LICENSE.rst
MANIFEST.in
README.rst
setup.cfg
setup.py
/home/joshua/Software/Current_MPInterfaces/MPInterfaces/mpinterfaces/scripts/__pycache__
/home/joshua/Software/Current_MPInterfaces/MPInterfaces/mpinterfaces/scripts/fabfile.py
/home/joshua/Software/Current_MPInterfaces/MPInterfaces/mpinterfaces/scripts/mpint
/home/joshua/Software/Current_MPInterfaces/MPInterfaces/mpinterfaces/scripts/smart_rlaunch.py
MPInterfaces_Latest.egg-info/PKG-INFO
MPInterfaces_Latest.egg-info/SOURCES.txt
MPInterfaces_Latest.egg-info/dependency_links.txt
MPInterfaces_Latest.egg-info/entry_points.txt
MPInterfaces_Latest.egg-info/requires.txt
MPInterfaces_Latest.egg-info/top_level.txt
examples/bands.py
examples/bands_dos.py
examples/create_interface.py
examples/create_slab.py
examples/dos.py
examples/eos.py
examples/hetero_interface.py
examples/lammps_jobs.py
examples/ligand_interface.py
examples/nanoparticle.py
examples/query_database.py
examples/smiles_to_xyz.py
examples/submit_data.py
examples/vasp_jobs.py
examples/notebooks/coulomb.ipynb
examples/notebooks/phasediagram.ipynb
examples/notebooks/pourbaix.ipynb
examples/notebooks/slab_ase.ipynb
examples/notebooks/.ipynb_checkpoints/pourbaix-checkpoint.ipynb
examples/workflows/fireworks_workflow.py
examples/workflows/lammps_workflow.py
examples/workflows/vasp_workflow.py
mpinterfaces/PBS_template.txt
mpinterfaces/SLURM_template.txt
mpinterfaces/__init__.py
mpinterfaces/analysis_temp.py
mpinterfaces/calibrate.py
mpinterfaces/data_processor.py
mpinterfaces/database.py
mpinterfaces/default_logger.py
mpinterfaces/firetasks.py
mpinterfaces/instrument.py
mpinterfaces/interface.py
mpinterfaces/lammps.py
mpinterfaces/measurement.py
mpinterfaces/mpint_cli.py
mpinterfaces/mpint_parser.py
mpinterfaces/nanoparticle.py
mpinterfaces/potcar_symbols.yaml
mpinterfaces/project_file.yaml
mpinterfaces/qtemplate.yaml
mpinterfaces/rest.py
mpinterfaces/transformations.py
mpinterfaces/utils.py
mpinterfaces/workflows.py
mpinterfaces/mat2d/__init__.py
mpinterfaces/mat2d/potcar_symbols.yaml
mpinterfaces/mat2d/electronic_structure/__init__.py
mpinterfaces/mat2d/electronic_structure/analysis.py
mpinterfaces/mat2d/electronic_structure/startup.py
mpinterfaces/mat2d/electronic_structure/tests/__init__.py
